sceleto2/README.rst
sceleto2/__init__.py
sceleto2/__init__.pyc
sceleto2/colors.py
sceleto2/data.py
sceleto2/draw.py
sceleto2/genes.py
sceleto2/genes.pyc
sceleto2/jhk.py
sceleto2/markers.py
sceleto2/mk_dick.pkl
sceleto2/model.py
sceleto2/network.py
sceleto2/readthedocs.yaml
sceleto2/species.py
sceleto2/utils.py
sceleto2/vdj.py
sceleto2/.git/COMMIT_EDITMSG
sceleto2/.git/FETCH_HEAD
sceleto2/.git/HEAD
sceleto2/.git/ORIG_HEAD
sceleto2/.git/config
sceleto2/.git/description
sceleto2/.git/index
sceleto2/.git/packed-refs
sceleto2/.git/hooks/applypatch-msg.sample
sceleto2/.git/hooks/commit-msg.sample
sceleto2/.git/hooks/fsmonitor-watchman.sample
sceleto2/.git/hooks/post-update.sample
sceleto2/.git/hooks/pre-applypatch.sample
sceleto2/.git/hooks/pre-commit.sample
sceleto2/.git/hooks/pre-merge-commit.sample
sceleto2/.git/hooks/pre-push.sample
sceleto2/.git/hooks/pre-rebase.sample
sceleto2/.git/hooks/pre-receive.sample
sceleto2/.git/hooks/prepare-commit-msg.sample
sceleto2/.git/hooks/update.sample
sceleto2/.git/info/exclude
sceleto2/.git/logs/HEAD
sceleto2/.git/logs/refs/heads/main
sceleto2/.git/logs/refs/remotes/origin/HEAD
sceleto2/.git/logs/refs/remotes/origin/main
sceleto2/.git/logs/refs/remotes/origin/patch1.1-documentation
sceleto2/.git/logs/refs/remotes/origin/patch1.2-documentation
sceleto2/.git/logs/refs/remotes/origin/patch2
sceleto2/.git/logs/refs/remotes/origin/patch3
sceleto2/.git/logs/refs/remotes/upstream/main
sceleto2/.git/logs/refs/remotes/upstream/patch1-documentation
sceleto2/.git/logs/refs/remotes/upstream/patch1.1-documentation
sceleto2/.git/logs/refs/remotes/upstream/patch1.2-documentation
sceleto2/.git/logs/refs/remotes/upstream/patch2
sceleto2/.git/logs/refs/remotes/upstream/patch3
sceleto2/.git/objects/00/a18c90556276846e8890d86eabf2811c807b80
sceleto2/.git/objects/01/50f70d89f649c87582f066246de67cbc473ee0
sceleto2/.git/objects/01/87c493c3c0d4e8b89c2fba5c2202ff6234e713
sceleto2/.git/objects/01/c254f8d459d40ce8630d895ae1d6bff2be0682
sceleto2-1.1.2.dist-info/LICENSE
sceleto2-1.1.2.dist-info/METADATA
sceleto2-1.1.2.dist-info/WHEEL
sceleto2-1.1.2.dist-info/top_level.txt
sceleto2-1.1.2.dist-info/RECORD
