Metadata-Version: 2.1
Name: sceleto2
Version: 1.1.2
Summary: sceleto2 is a wrapper package developed by SCMGL to aid in single cell analysis.
Home-page: UNKNOWN
Author: Jongeun Park
Author-email: jp24@kaist.ac.kr
License: MIT
Keywords: sceleto,single cell,scRNA-seq
Platform: UNKNOWN
Requires-Python: >=3.7
Requires-Dist: adjustText
Requires-Dist: bbknn
Requires-Dist: datetime
Requires-Dist: diffxpy
Requires-Dist: geosketch
Requires-Dist: harmonypy
Requires-Dist: joblib
Requires-Dist: matplotlib
Requires-Dist: networkx
Requires-Dist: numba
Requires-Dist: numpy
Requires-Dist: pandas
Requires-Dist: python-igraph
Requires-Dist: scanpy
Requires-Dist: scikit-learn
Requires-Dist: scipy
Requires-Dist: scrublet
Requires-Dist: seaborn
